{"$schema":"https://json-schema.org/draft/2020-12/schema","$id":"https://homeworldmodel.org/spec/profiles/value-clarification-dialogue/v0.1/value-response-interpretation.schema.json","title":"HWM Value Response Interpretation v0.1","type":"object","required":["contract","contract_version","interpretation_id","question_proposal_binding","response_record_binding","respondent_binding","response_meaning","question_currency_status","respondent_authority_status","evidence_standing_status","scope_alignment_status","purpose_alignment_status","disclosure_authorization_status","result","candidate_claim_scope","reason_codes","interpreted_at","proof","extensions"],"properties":{"contract":{"const":"hwm-value:ValueResponseInterpretation"},"contract_version":{"const":"0.1.0"},"interpretation_id":{"type":"string","minLength":1},"question_proposal_binding":{"$ref":"#/$defs/Binding"},"response_record_binding":{"$ref":"#/$defs/Binding"},"respondent_binding":{"$ref":"#/$defs/Binding"},"response_meaning":{"enum":["prefer_left_for_scope","prefer_right_for_scope","indifferent_for_scope","accept_declared_tradeoff_rule","defer","cannot_tell","reject_premise","correct_scope_or_options","unrecoverable"]},"question_currency_status":{"enum":["current","expired","superseded","indeterminate"]},"respondent_authority_status":{"enum":["authorized_for_self","authorized_representative","not_authorized","indeterminate"]},"evidence_standing_status":{"enum":["accepted","denied","indeterminate"]},"scope_alignment_status":{"enum":["aligned","out_of_scope","indeterminate"]},"purpose_alignment_status":{"enum":["aligned","mismatch","indeterminate"]},"disclosure_authorization_status":{"enum":["allowed","denied","indeterminate"]},"result":{"enum":["candidate_value_claim_eligible","no_value_claim","question_revision_required","not_eligible","indeterminate"]},"candidate_claim_scope":{"oneOf":[{"type":"null"},{"type":"object","required":["subject_binding","option_or_target_bindings","relation","context_binding","purpose","valid_from","valid_until","limitations"],"properties":{"subject_binding":{"$ref":"#/$defs/Binding"},"option_or_target_bindings":{"type":"array","minItems":2,"items":{"$ref":"#/$defs/Binding"}},"relation":{"enum":["prefers_left","prefers_right","indifferent_for_scope","accepts_declared_rule"]},"context_binding":{"$ref":"#/$defs/Binding"},"purpose":{"type":"string","minLength":1},"valid_from":{"type":"string","format":"date-time"},"valid_until":{"type":"string","format":"date-time"},"limitations":{"type":"array","minItems":1,"items":{"type":"string","minLength":1}}},"additionalProperties":false}]},"reason_codes":{"type":"array","minItems":1,"items":{"type":"string","minLength":1}},"interpreted_at":{"type":"string","format":"date-time"},"proof":{"$ref":"#/$defs/Proof"},"extensions":{"type":"object"}},"$defs":{"Digest":{"type":"string","pattern":"^[0-9a-f]{64}$"},"Binding":{"type":"object","required":["artifact_id","revision","digest_algorithm","canonicalization","digest"],"properties":{"artifact_id":{"type":"string","minLength":1},"revision":{"type":"integer","minimum":1},"digest_algorithm":{"const":"sha-256"},"canonicalization":{"const":"RFC8785"},"digest":{"$ref":"#/$defs/Digest"}},"additionalProperties":false},"Proof":{"type":"object","required":["mode","verification_method","value"],"properties":{"mode":{"enum":["unsigned_fixture","jws","cose","vc"]},"verification_method":{"type":"string","minLength":1},"value":{"type":"string","minLength":1}},"additionalProperties":false}},"additionalProperties":false}
